rankgen/__init__.py
rankgen/ab_tests.py
rankgen/ab_tests_generations.py
rankgen/avg_lengths.py
rankgen/build_new_ab_split.py
rankgen/choose_examples.py
rankgen/convert_checkpoint.py
rankgen/export_results.py
rankgen/gpt2_generate.py
rankgen/gpt2_score.py
rankgen/gpt3_score.py
rankgen/human_eval.py
rankgen/parallel/merge.py
rankgen/parallel/parallel_logs/.gitkeep
rankgen/parallel/parallel_schedulers/.gitkeep
rankgen/parallel/parallel_template_gpu.sh
rankgen/parallel/schedule.py
rankgen/plot_divergence_curves.py
rankgen/preprocess_story_cloze.py
rankgen/rankgen_beam_search.py
rankgen/rankgen_beam_search_choose_eg.py
rankgen/rankgen_beam_search_shifting.py
rankgen/rankgen_encoder.py
rankgen/rankgen_generator.py
rankgen/retriever_score.py
rankgen/score_ab.py
rankgen/score_ab_text.py
rankgen/score_multi.py
rankgen/score_multi_beam.py
rankgen/score_multi_tsv.py
rankgen/shorten_prefix.py
rankgen/shorten_suffix.py
rankgen/test_rankgen_encoder.py
rankgen/token_overlap.py
rankgen/token_overlap_generate.py
rankgen/utils.py
rankgen-0.1.1.dist-info/LICENSE
rankgen-0.1.1.dist-info/WHEEL
rankgen-0.1.1.dist-info/METADATA
rankgen-0.1.1.dist-info/RECORD
