Metadata-Version: 2.1
Name: rankgen
Version: 0.1.1
Summary: RankGen is a suite of encoder models (100M-1.2B parameters) which map prefixes and generations from any pretrained English language model to a shared vector space. RankGen can be used to rerank multiple full-length samples from an LM, and it can also be incorporated as a scoring function into beam search to significantly improve generation quality (0.85 vs 0.77 MAUVE, 75% preference according to humans annotators who are English writers).
Home-page: https://github.com/martiansideofthemoon/rankgen
License: Apache-2.0
Author: Kalpesh Krishna, Yapei Chang, John Wieting, Mohit Iyyer
Requires-Python: >=3.7,<4.0
Classifier: License :: OSI Approved :: Apache Software License
Classifier: Programming Language :: Python :: 3
Classifier: Programming Language :: Python :: 3.10
Classifier: Programming Language :: Python :: 3.7
Classifier: Programming Language :: Python :: 3.8
Classifier: Programming Language :: Python :: 3.9
Requires-Dist: gdown (>=4.5.1,<5.0.0)
Requires-Dist: sentencepiece (>=0.1.96,<0.2.0)
Requires-Dist: torch (>=1.12.0,<2.0.0)
Requires-Dist: transformers (>=4.20.1,<5.0.0)
Project-URL: Repository, https://github.com/martiansideofthemoon/rankgen
